drug_suggestor/__init__.py
drug_suggestor/__version__.py
drug_suggestor/main.py
drug_suggestor/v1/__init__.py
drug_suggestor/v1/main.py
drug_suggestor/v1/models/__init__.py
drug_suggestor/v1/models/disease.py
drug_suggestor/v1/models/drug.py
drug_suggestor/v1/models/patient.py
drug_suggestor/v1/templates/__init__.py
drug_suggestor-0.0.0.dist-info/LICENSE.md
drug_suggestor-0.0.0.dist-info/METADATA
drug_suggestor-0.0.0.dist-info/WHEEL
drug_suggestor-0.0.0.dist-info/RECORD
