Metadata-Version: 2.1
Name: drug-suggestor
Version: 0.0.0
Summary: Suggest Drugs based on symptoms or images or description
Author: Vamsidhar Reddy
Author-email: r.vamsireddy93@gmail.com
Requires-Python: >=3.11,<3.12
Classifier: Programming Language :: Python :: 3
Classifier: Programming Language :: Python :: 3.11
Requires-Dist: langchain (>=0.0.345,<0.0.346)
Requires-Dist: pydantic (>=2.4.2,<3.0.0)
